secretenv/__init__.py
secretenv/__main__.py
secretenv-0.1.5.dist-info/METADATA
secretenv-0.1.5.dist-info/WHEEL
secretenv-0.1.5.dist-info/top_level.txt
secretenv-0.1.5.dist-info/RECORD
