Metadata-Version: 2.1
Name: secretenv
Version: 0.1.5
Summary: Playing with a secrets-in-repo idea.
Home-page: https://github.com/gmfawcett/secretenv
Author: gmfawcett
Author-email: graham.fawcett@gmail.com
License: MIT
Platform: UNKNOWN
Requires-Python: >=3.8
Requires-Dist: scrypt (==0.8.18)
